docsloader/__init__.py
docsloader/_auto.py
docsloader/_csv.py
docsloader/_docx.py
docsloader/_html.py
docsloader/_md.py
docsloader/_pptx.py
docsloader/_txt.py
docsloader/_xlsx.py
docsloader/base.py
docsloader/_img/__init__.py
docsloader/_img/_rapidocr.py
docsloader/_img/_tesseract.py
docsloader/_pdf/__init__.py
docsloader/_pdf/_pdfplumber.py
docsloader/_pdf/_pymupdf.py
docsloader/utils/__init__.py
docsloader/utils/_download_to_tmpfile.py
docsloader/utils/_format_image.py
docsloader/utils/_format_table.py
docsloader/utils/_is_empty_file.py
docsloader/utils/_mk_tmpdir.py
docsloader/utils/_office_cvt_openxml.py
docsloader/utils/_rm_dir.py
docsloader/utils/_rm_empty_dir.py
docsloader/utils/_rm_file.py
docsloader-0.0.13.dist-info/licenses/LICENSE
docsloader-0.0.13.dist-info/METADATA
docsloader-0.0.13.dist-info/WHEEL
docsloader-0.0.13.dist-info/top_level.txt
docsloader-0.0.13.dist-info/RECORD
