Metadata-Version: 2.4
Name: docsloader
Version: 0.0.13
Summary: This is a documents loader.
Author-email: axiner <atpuxiner@163.com>
Project-URL: Homepage, https://github.com/atpuxiner/docsloader
Classifier: Programming Language :: Python :: 3.11
Classifier: Operating System :: OS Independent
Requires-Python: >=3.11
License-File: LICENSE
Requires-Dist: toollib>=1.9.7
Requires-Dist: pydantic>=2.12.5
Requires-Dist: aiofiles>=25.1.0
Requires-Dist: aiohttp>=3.13.2
Requires-Dist: pywin32>=311; platform_system == "Windows"
Provides-Extra: txt
Provides-Extra: csv
Provides-Extra: md
Provides-Extra: html
Requires-Dist: lxml>=6.0.2; extra == "html"
Provides-Extra: xlsx
Requires-Dist: openpyxl>=3.1.5; extra == "xlsx"
Requires-Dist: xlrd>=2.0.2; extra == "xlsx"
Provides-Extra: pptx
Requires-Dist: python-pptx>=1.0.2; extra == "pptx"
Provides-Extra: docx
Requires-Dist: python-docx>=1.2.0; extra == "docx"
Provides-Extra: pdf
Requires-Dist: pymupdf>=1.26.7; extra == "pdf"
Requires-Dist: numpy; extra == "pdf"
Provides-Extra: img
Requires-Dist: rapidocr-onnxruntime>=1.4.4; extra == "img"
Provides-Extra: auto
Requires-Dist: docsloader[txt]; extra == "auto"
Requires-Dist: docsloader[csv]; extra == "auto"
Requires-Dist: docsloader[md]; extra == "auto"
Requires-Dist: docsloader[html]; extra == "auto"
Requires-Dist: docsloader[xlsx]; extra == "auto"
Requires-Dist: docsloader[pptx]; extra == "auto"
Requires-Dist: docsloader[docx]; extra == "auto"
Requires-Dist: docsloader[pdf]; extra == "auto"
Requires-Dist: docsloader[img]; extra == "auto"
Provides-Extra: all
Requires-Dist: docsloader[auto]; extra == "all"
Dynamic: license-file
